Metadata-Version: 2.1
Name: cbw-api-toolbox
Version: 2.3.2
Summary: CyberWatch Api Tools.
Home-page: https://github.com/Cyberwatch/cyberwatch_api_toolbox
Author: CyberWatch SAS
Author-email: support-it+api@cyberwatch.fr
License: MIT
Project-URL: Documentation, https://docs.cyberwatch.fr/api/#introduction
License-File: LICENSE
Requires-Dist: requests (>=2.20.1)
Requires-Dist: XlsxWriter (>=1.2.1)
Requires-Dist: openpyxl (>=3.0.6)
Requires-Dist: python-dateutil (>=2.8.1)
Requires-Dist: chardet (>=3.0.4)
